LICENSE
MANIFEST.in
README.rst
setup.py
django_nullablecharfield.egg-info/PKG-INFO
django_nullablecharfield.egg-info/SOURCES.txt
django_nullablecharfield.egg-info/dependency_links.txt
django_nullablecharfield.egg-info/top_level.txt
nullablecharfield/__init__.py
nullablecharfield/models.py
nullablecharfield/widgets.py
nullablecharfield/db/__init__.py
nullablecharfield/db/models/__init__.py
nullablecharfield/db/models/fields.py
nullablecharfield/forms/__init__.py
nullablecharfield/forms/fields.py
nullablecharfield/static/js/nullabletext.js