Metadata-Version: 1.1
Name: django-nullablecharfield
Version: 0.2.2
Summary: A simple Django app that allow the use of Nullable char field.
Home-page: https://github.com/alepane21/django-nullablecharfield
Author: Alessandro Pagnin
Author-email: alepane@gmail.com
License: BSD License
Platform: UNKNOWN
Classifier: Environment :: Web Environment
Classifier: Framework :: Django
Classifier: Intended Audience :: Developers
Classifier: License :: OSI Approved :: BSD License
Classifier: Operating System :: OS Independent
Classifier: Programming Language :: Python
Classifier: Programming Language :: Python :: 2
Classifier: Programming Language :: Python :: 2.7
Classifier: Topic :: Internet :: WWW/HTTP
Classifier: Topic :: Internet :: WWW/HTTP :: Dynamic Content
